{
  "generated_at": "2026-06-09T19:23:10.470Z",
  "source": "ojk-indonesia",
  "source_url": "https://www.ojk.go.id/en/",
  "company_count": 1,
  "skipped_unresolved": 0,
  "companies": {
    "pertamina": {
      "raw_name": "PT Pertamina (Persero)",
      "case_count": 1,
      "latest_year": 2023,
      "summary": "OJK oversight + Indonesian KPPU (competition) sanctions on Pertamina pricing practices; multiple administrative actions documented.",
      "url": "https://www.ojk.go.id/en/"
    }
  }
}