{
  "source": "disability-in",
  "source_url": "https://disabilityin.org/what-we-do/disability-equality-index/",
  "fetched_at": "2026-06-07T19:47:09.923Z",
  "mode": "dry",
  "record_count": 10,
  "records": [
    {
      "company": "Microsoft Corporation",
      "dei_score": 100,
      "year": 2024
    },
    {
      "company": "The Boeing Company",
      "dei_score": 100,
      "year": 2024
    },
    {
      "company": "Walmart Inc.",
      "dei_score": 90,
      "year": 2024
    },
    {
      "company": "Pfizer Inc.",
      "dei_score": 100,
      "year": 2024
    },
    {
      "company": "JPMorgan Chase & Co.",
      "dei_score": 100,
      "year": 2024
    },
    {
      "company": "Apple Inc.",
      "dei_score": 80,
      "year": 2024
    },
    {
      "company": "Bank of America Corporation",
      "dei_score": 100,
      "year": 2024
    },
    {
      "company": "Comcast Corporation",
      "dei_score": 90,
      "year": 2024
    },
    {
      "company": "Procter & Gamble Co.",
      "dei_score": 100,
      "year": 2024
    },
    {
      "company": "Ford Motor Company",
      "dei_score": 90,
      "year": 2024
    }
  ]
}