{
  "slug": "acxiom",
  "name": "Acxiom",
  "status": "ok",
  "total_obligated_USD_last_5y": 7905094,
  "award_count_last_5y": 2,
  "recent_top5": [
    {
      "date": "2018-05-01",
      "agency": "Department of State",
      "naics": {
        "code": "541519",
        "description": "OTHER COMPUTER RELATED SERVICES"
      },
      "amount": 5273138.9,
      "description": "DS INFORMATION MANAGEMENT SYSTEM (IMS) - IT CONSULTATION SERVICES - SUPPORTING DS/ICI/CR/VPAU IGF::OT::IGF"
    },
    {
      "date": "2022-05-01",
      "agency": "Department of State",
      "naics": {
        "code": "541519",
        "description": "OTHER COMPUTER RELATED SERVICES"
      },
      "amount": 2631955.22,
      "description": "SPECIALIZED SME IT CONSULTING SERVICES AND RAPID DEVELOPMENT SUPPORT RELATED TO THE INVESTIGATIVE MANAGEMENT SYSTEM (IMS). INVESTIGATION MANAGEMENT SYSTEM IN VPAU."
    }
  ],
  "primary_agency": "Department of State",
  "primary_naics": "[object Object]",
  "last_updated": "2026-06-11T23:33:17.675Z",
  "source_url": "https://api.usaspending.gov/api/v2/search/spending_by_award/",
  "_orphan": false
}