{
  "slug": "alcon",
  "name": "ALCON",
  "status": "ok",
  "total_obligated_USD_last_5y": 1020428527,
  "award_count_last_5y": 500,
  "recent_top5": [
    {
      "date": "2021-12-10",
      "agency": "Department of Defense",
      "naics": {
        "code": "541330",
        "description": "ENGINEERING SERVICES"
      },
      "amount": 183247960.21,
      "description": "ENGINEERING AND LOGISTICS CONTRACTOR SUPPORT SERVICES IN SUPPORT OF PEO DIGITAL."
    },
    {
      "date": "2017-05-26",
      "agency": "Department of Defense",
      "naics": {
        "code": "541330",
        "description": "ENGINEERING SERVICES"
      },
      "amount": 170912175.62,
      "description": "IGF::OT::IGF PEO-EIS PORTFOLIO LOGISTICS AND ENGINEERING SUPPORT"
    },
    {
      "date": "2017-07-28",
      "agency": "Department of Defense",
      "naics": {
        "code": "541712",
        "description": "RESEARCH AND DEVELOPMENT IN THE PHYSICAL, ENGINEERING, AND LIFE SCIENCES (EXCEPT BIOTECHNOLOGY)"
      },
      "amount": 88888940.59,
      "description": "IGF::CT::IGF AMCOM/ADD AIRFIELD SUPPORT - BASE"
    },
    {
      "date": "2015-05-06",
      "agency": "Department of Defense",
      "naics": {
        "code": "541712",
        "description": "RESEARCH AND DEVELOPMENT IN THE PHYSICAL, ENGINEERING, AND LIFE SCIENCES (EXCEPT BIOTECHNOLOGY)"
      },
      "amount": 55954565.99,
      "description": "IGF::CL::IGF SCAT1 ADMINISTRATIVE SUPPORT SERVICES (EPASS) ADVISORY AND ASSISTANCE SERVICES (A&AS) SUPPORT OF TANKER DIRECTORATE (AFLCMC/WK) RFP #3 TANKER"
    },
    {
      "date": "2021-07-30",
      "agency": "Department of Defense",
      "naics": {
        "code": "541330",
        "description": "ENGINEERING SERVICES"
      },
      "amount": 42888134.53,
      "description": "ENGINEERING AND LOGISTICS SERVICES IN SUPPORT OF PEO MLB PMW 220."
    }
  ],
  "primary_agency": "Department of Defense",
  "primary_naics": "[object Object]",
  "last_updated": "2026-06-11T23:38:24.547Z",
  "source_url": "https://api.usaspending.gov/api/v2/search/spending_by_award/",
  "_orphan": false
}