{
  "name": "Idexx Laboratories",
  "legalName": "IDEXX LABORATORIES INC /DE",
  "cat": "Healthcare",
  "init": "IDXX",
  "overall": null,
  "realCats": 0,
  "isPublic": true,
  "ticker": "IDXX",
  "cik": 874716,
  "sic": 2835,
  "sicDescription": "In Vitro & In Vivo Diagnostic Substances",
  "addedBy": "edgar-expansion-2026-06",
  "sc": {
    "political": "neutral",
    "charity": "neutral",
    "environment": "neutral",
    "labor": "neutral",
    "dei": "neutral",
    "animals": "neutral",
    "guns": "neutral",
    "privacy": "neutral",
    "execPay": "neutral",
    "health": "neutral"
  },
  "political": {
    "s": "No public record found.",
    "sources": []
  },
  "charity": {
    "s": "No public record found.",
    "sources": []
  },
  "environment": {
    "s": "No public record found.",
    "sources": []
  },
  "labor": {
    "s": "No public record found.",
    "sources": []
  },
  "dei": {
    "s": "EEO-1 workforce demographics on federal record (FY2017, DOL OFCCP FOIA release): 5,199 US employees — 54% women, 21.1% racial/ethnic minorities; management 43.4% women, 12.1% minorities.",
    "sources": [
      "ofccp-eeo1"
    ]
  },
  "animals": {
    "s": "No public record found.",
    "sources": []
  },
  "guns": {
    "s": "No public record found.",
    "sources": []
  },
  "privacy": {
    "s": "No public record found.",
    "sources": []
  },
  "execPay": {
    "s": "No public record found.",
    "sources": []
  },
  "health": {
    "s": "No public record found.",
    "sources": []
  },
  "ab": "#0f0d21",
  "ac": "#6759cf",
  "competitors": [],
  "slug": "idexx-laboratories-de",
  "flags": {
    "guns": {
      "na": true
    },
    "dei": {
      "notDisclosed": true
    },
    "charity": {
      "notDisclosed": true
    },
    "transparency": {
      "notDisclosed": true
    },
    "environment": {
      "_inferred": true,
      "basis": "Healthcare"
    }
  },
  "dei_eeo1": {
    "year": 2017,
    "totalEmployees": 5199,
    "pctWomen": 54,
    "pctMinority": 21.1,
    "pctWomenMgmt": 43.4,
    "pctMinorityMgmt": 12.1,
    "source": "DOL OFCCP FOIA — Type 2 EEO-1",
    "sourceUrl": "https://www.dol.gov/agencies/ofccp/foia/library/Employment-Information-Reports"
  },
  "enriched": {
    "secTax": {
      "effectiveTaxRate": 0.2,
      "taxExpenseUsd": 221964000,
      "pretaxIncomeUsd": 1109831000,
      "year": 2024,
      "cik": 874716,
      "source": "SEC EDGAR XBRL"
    }
  },
  "dataLastUpdated": {
    "enrichedAugments": "2026-06-26T16:16:39.453Z"
  }
}