{"name":"Millennium Group International Holdings","legalName":"Millennium Group International Holdings Ltd","cat":"Manufacturing","init":"MGIH","overall":null,"realCats":0,"isPublic":true,"ticker":"MGIH","cik":1903995,"sic":2750,"sicDescription":"Commercial Printing","addedBy":"edgar-expansion-2026-06","sc":{"political":"neutral","charity":"neutral","environment":"neutral","labor":"neutral","dei":"neutral","animals":"neutral","guns":"neutral","privacy":"neutral","execPay":"neutral","health":"neutral"},"political":{"s":"No public record found.","sources":[]},"charity":{"s":"No public record found.","sources":[]},"environment":{"s":"No public record found.","sources":[]},"labor":{"s":"No public record found.","sources":[]},"dei":{"s":"No public record found.","sources":[]},"animals":{"s":"No public record found.","sources":[]},"guns":{"s":"No public record found.","sources":[]},"privacy":{"s":"No public record found.","sources":[]},"execPay":{"s":"No public record found.","sources":[]},"health":{"s":"No public record found.","sources":[]},"ab":"#1e0d21","ac":"#bd59cf","competitors":[],"slug":"millennium-international","flags":{"guns":{"na":true},"health":{"na":true},"dei":{"notDisclosed":true},"charity":{"notDisclosed":true},"transparency":{"notDisclosed":true},"environment":{"_inferred":true,"basis":"Manufacturing"}},"enriched":{"secTax":{"effectiveTaxRate":-0.02,"taxExpenseUsd":206944,"pretaxIncomeUsd":-8563100,"year":2024,"cik":1903995,"source":"SEC EDGAR XBRL"}},"dataLastUpdated":{"enrichedAugments":"2026-06-26T16:16:39.453Z"}}