{"name":"Plymouth","cat":"Retail","init":"PLYM","overall":50,"isPublic":true,"sc":{"political":"neutral","charity":"neutral","environment":"neutral","labor":"neutral","dei":"neutral","animals":"na","guns":"neutral","privacy":"na","execPay":"na"},"political":{"s":"No public record found.","sources":["Public records research"]},"labor":{"s":"No public record found.","sources":["Public records research"]},"dataLastUpdated":"2026-05-31","charity":{"s":"No public record found.","sources":["Public records research"]},"environment":{"s":"No public record found.","sources":["Public records research"]},"dei":{"s":"No public record found.","sources":["Public records research"]},"animals":{"s":"No public record found.","sources":["Public records research"]},"guns":{"s":"No public record found.","sources":[]},"privacy":{"s":"No public record found.","sources":["Public records research"]},"execPay":{"s":"No public record found.","sources":["Public records research"]},"ab":"#0d2318","ac":"#4caf82","wiki":{"founded":"1928-07-07","hq":"Auburn Hills","employees":null,"revenue":null,"parent":"Stellantis North America","industry":"automotive industry","products":null,"keyPeople":"Walter Percy Chrysler Sr.","website":null,"controversies":null,"logoUrl":"https://upload.wikimedia.org/wikipedia/en/thumb/0/03/Plymouth_logo.svg/330px-Plymouth_logo.svg.png","wikipediaUrl":"https://en.wikipedia.org/wiki/Plymouth_(automobile)","extract":"Plymouth was a brand of automobiles produced by Chrysler Corporation and its successor DaimlerChrysler. The brand was launched in 1928 to compete in what was then described as the \"low-priced\" market segment that was dominated by Chevrolet and Ford. It became a high-volume seller for the automaker until the late 1990s. Plymouth cars were marketed primarily in the United States and Canada. The brand was withdrawn from the marketplace in 2001. The Plymouth models that were produced up until then were either discontinued or rebranded as Chrysler or Dodge."},"bbb":{"rating":"A+","accredited":null,"complaintCount":null,"profileUrl":"https://www.bbb.org/us/ne/plymouth/profile/electrician/plymouth-electric-0714-216002028"},"secComplaints":{"count":61,"sample":[{"adsh":"0001140361-25-012719","date":"2025-04-08","filer":"Accolade, Inc.  (ACCD)  (CIK 0001481646)","form":"8-K"},{"adsh":"0001104659-26-042886","date":"2026-04-14","filer":"Harmony Biosciences Holdings, Inc.  (HRMY)  (CIK 0001802665)","form":"8-K"},{"adsh":"0001140361-25-012719","date":"2025-04-08","filer":"Accolade, Inc.  (ACCD)  (CIK 0001481646)","form":"8-K"}]},"logoUrl":"https://commons.wikimedia.org/wiki/Special:FilePath/Plymouth%20brand%20logo%201964.png","logoSource":"wikidata_p154","slug":"plymouth","competitors":[],"news":null,"payRatio":null,"deiBadges":null,"animalCerts":null,"products":null,"storeFootprint":null,"recalls":null,"origin":null,"ownership":null,"charity_irs990":null,"firearms_atf_ffl":null,"environment_ejscreen":null,"ownership_wikidata":null,"privacy_hibp_breaches":null,"litigation_courtlistener":null,"labor_dol_whd":null,"violationTracker":null,"fec":null,"sec":{"source":"SEC EDGAR","filingFound":true,"filingDate":"2024-04-29","filingUrl":"https://www.sec.gov/cgi-bin/browse-edgar?action=getcompany&company=Plymouth&type=DEF+14A&dateb=&owner=include&count=10","note":"Pay ratio extracted from proxy filing — verify manually for accuracy","fetchedAt":"2026-05-31T01:52:44.364Z"},"osha":null,"nlrb":null,"epa":null,"lastUpdated":"2026-05-31T01:52:44.364Z","flags":{"dei":{"notDisclosed":true},"charity":{"notDisclosed":true},"transparency":{"notDisclosed":true},"environment":{"_inferred":true,"basis":"Retail"}}}