{
  "name": "Rpm International",
  "legalName": "RPM INTERNATIONAL INC/DE/",
  "cat": "Manufacturing",
  "init": "RPM",
  "overall": null,
  "realCats": 0,
  "isPublic": true,
  "ticker": "RPM",
  "cik": 110621,
  "sic": 2851,
  "sicDescription": "Paints, Varnishes, Lacquers, Enamels & Allied Prods",
  "addedBy": "edgar-expansion-2026-06",
  "sc": {
    "political": "neutral",
    "charity": "neutral",
    "environment": "neutral",
    "labor": "neutral",
    "dei": "neutral",
    "animals": "neutral",
    "guns": "neutral",
    "privacy": "neutral",
    "execPay": "neutral",
    "health": "neutral"
  },
  "political": {
    "s": "No public record found.",
    "sources": []
  },
  "charity": {
    "s": "No public record found.",
    "sources": []
  },
  "environment": {
    "s": "No public record found.",
    "sources": []
  },
  "labor": {
    "s": "No public record found.",
    "sources": []
  },
  "dei": {
    "s": "EEO-1 workforce demographics on federal record (FY2020, DOL OFCCP FOIA release): 8,279 US employees — 22.1% women, 26.6% racial/ethnic minorities; management 19.8% women, 11.2% minorities.",
    "sources": [
      "ofccp-eeo1"
    ]
  },
  "animals": {
    "s": "No public record found.",
    "sources": []
  },
  "guns": {
    "s": "No public record found.",
    "sources": []
  },
  "privacy": {
    "s": "No public record found.",
    "sources": []
  },
  "execPay": {
    "s": "No public record found.",
    "sources": []
  },
  "health": {
    "s": "No public record found.",
    "sources": []
  },
  "ab": "#210d1e",
  "ac": "#cf59bd",
  "competitors": [],
  "slug": "rpm-international-de",
  "flags": {
    "guns": {
      "na": true
    },
    "health": {
      "na": true
    },
    "dei": {
      "notDisclosed": true
    },
    "charity": {
      "notDisclosed": true
    },
    "transparency": {
      "notDisclosed": true
    },
    "environment": {
      "_inferred": true,
      "basis": "Manufacturing"
    }
  },
  "dei_eeo1": {
    "year": 2020,
    "totalEmployees": 8279,
    "pctWomen": 22.1,
    "pctMinority": 26.6,
    "pctWomenMgmt": 19.8,
    "pctMinorityMgmt": 11.2,
    "source": "DOL OFCCP FOIA — Type 2 EEO-1",
    "sourceUrl": "https://www.dol.gov/agencies/ofccp/foia/library/Employment-Information-Reports"
  },
  "enriched": {
    "secTax": {
      "effectiveTaxRate": 0.129,
      "taxExpenseUsd": 102433000,
      "pretaxIncomeUsd": 792760000,
      "year": 2024,
      "cik": 110621,
      "source": "SEC EDGAR XBRL"
    },
    "supplyChain": {
      "conflictMineralsFiler": true,
      "_sec": {
        "cik": "110621",
        "displayName": "RPM INTERNATIONAL INC"
      },
      "lastUpdated": "2026-06-26T16:14:03.087Z"
    }
  },
  "dataLastUpdated": {
    "enrichedAugments": "2026-06-26T16:16:39.453Z"
  }
}