{"name":"Strats(Sm) Trust For Dominion Resources, Inc. Securities, Series 2005-6","legalName":"STRATS(SM) TRUST FOR DOMINION RESOURCES, INC. SECURITIES, SERIES 2005-6","cat":"Financial Services","init":"GJP","overall":null,"realCats":0,"isPublic":true,"ticker":"GJP","cik":1343491,"sic":6189,"sicDescription":"Asset-Backed Securities","addedBy":"edgar-expansion-2026-06","sc":{"political":"neutral","charity":"neutral","environment":"neutral","labor":"neutral","dei":"neutral","animals":"neutral","guns":"neutral","privacy":"neutral","execPay":"neutral","health":"neutral"},"political":{"s":"No public record found.","sources":[]},"charity":{"s":"No public record found.","sources":[]},"environment":{"s":"No public record found.","sources":[]},"labor":{"s":"No public record found.","sources":[]},"dei":{"s":"No public record found.","sources":[]},"animals":{"s":"No public record found.","sources":[]},"guns":{"s":"No public record found.","sources":[]},"privacy":{"s":"No public record found.","sources":[]},"execPay":{"s":"No public record found.","sources":[]},"health":{"s":"No public record found.","sources":[]},"ab":"#110d21","ac":"#7459cf","competitors":[],"slug":"strats-sm-trust-for-dominion-resources-securities-series-2005-6","flags":{"animals":{"na":true},"guns":{"na":true},"health":{"na":true},"dei":{"notDisclosed":true},"charity":{"notDisclosed":true},"transparency":{"notDisclosed":true},"environment":{"_inferred":true,"basis":"Financial Services"}}}