{"name":"Telvantis","cat":"Other","init":"TELV","overall":50,"isPublic":false,"sc":{"political":"neutral","charity":"neutral","environment":"neutral","labor":"neutral","dei":"neutral","animals":"na","guns":"neutral","privacy":"na","execPay":"na"},"political":{"s":"No public record found.","sources":["Public records research"]},"labor":{"s":"No public record found.","sources":["Public records research"]},"dataLastUpdated":"2026-05-28","charity":{"s":"No public record found.","sources":["Public records research"]},"environment":{"s":"No public record found.","sources":["Public records research"]},"dei":{"s":"No public record found.","sources":["Public records research"]},"animals":{"s":"No public record found.","sources":["Public records research"]},"guns":{"s":"No public record found.","sources":[]},"privacy":{"s":"No public record found.","sources":["Public records research"]},"execPay":{"s":"No public record found.","sources":["Public records research"]},"ab":"#0d2318","ac":"#4caf82","competitors":[],"wiki":{"founded":null,"hq":null,"employees":null,"revenue":null,"parent":null,"industry":null,"products":null,"keyPeople":null,"website":"[http://www.ast-group.ru/ AST Group Website]","controversies":null,"logoUrl":null,"wikipediaUrl":"https://en.wikipedia.org/wiki/Telman_Ismailov","extract":"Telman Mardanovich Ismailov (Azerbaijani: Telman Mərdan oğlu İsmayılov, Russian: Те́льман Марда́нович Исмаи́лов; born 26 October 1956) is an Azerbaijani-born Russian businessman and entrepreneur of Mountain Jewish origin. Since Azerbaijan does not allow dual citizenship, he holds Russian-Turkish citizenship. He is the chairman of the Russian AST Group of companies, which is active in many countries. Until 2009, Ismailov owned the Europe's then-largest marketplace, Cherkizovsky Market, located in Moscow, Russia."},"slug":"telvantis","bbb":null,"secComplaints":null,"news":null,"payRatio":null,"deiBadges":null,"animalCerts":null,"logoUrl":null,"logoSource":null,"products":null,"storeFootprint":null,"recalls":null,"origin":null,"ownership":null,"charity_irs990":null,"firearms_atf_ffl":null,"environment_ejscreen":null,"ownership_wikidata":null,"privacy_hibp_breaches":null,"litigation_courtlistener":null,"labor_dol_whd":null,"violationTracker":null,"fec":null,"sec":null,"osha":null,"nlrb":null,"epa":null,"lastUpdated":null,"flags":{"execPay":{"notDisclosed":true},"dei":{"notDisclosed":true},"charity":{"notDisclosed":true},"transparency":{"notDisclosed":true},"environment":{"_inferred":true,"basis":"Other"}}}